s3nosqldb/__init__.py
s3nosqldb/core.py
s3nosqldb/exceptions.py
s3nosqldb-0.1.1.dist-info/LICENSE
s3nosqldb-0.1.1.dist-info/METADATA
s3nosqldb-0.1.1.dist-info/WHEEL
s3nosqldb-0.1.1.dist-info/top_level.txt
s3nosqldb-0.1.1.dist-info/RECORD
